[
    {
        "symbol": "ZRC",
        "start_time": "",
        "official_website": "https://www.0xproject.com/#home",
        "status": "ICO coming",
        "logo": "../logo/ZRC.png",
        "address": [],
        "name": "0x Project",
        "description": "The protocol for decentralized exchange",
        "end_time": ""
    },
    {
        "symbol": "21MCoin",
        "start_time": "12. Jun 2017",
        "official_website": "https://www.21million.co.uk/",
        "status": "ICO coming",
        "logo": "../logo/21MCoin.png",
        "address": [],
        "name": "21 Million",
        "description": "Crypto-funded blockchain indy tv series",
        "end_time": "28. Jun 2017"
    },
    {
        "symbol": "Akasha",
        "start_time": "",
        "official_website": "https://bittrex.com/Market/Index?MarketName=BTC-AGRS",
        "status": "ICO coming",
        "logo": "../logo/Akasha.png",
        "address": [],
        "name": "Akasha",
        "description": "Ethereum based social network using IPFS for storage",
        "end_time": ""
    },
    {
        "symbol": "ANT",
        "start_time": "17. May 2017",
        "official_website": "https://aragon.one/",
        "status": "Trading",
        "logo": "../logo/ANT.png",
        "address": [
            "0x960b236A07cf122663c4303350609A66A7B288C0"
        ],
        "name": "Aragon",
        "description": "Create value without borders or intermediaries",
        "end_time": "17. May 2017"
    },
    {
        "symbol": "REP",
        "start_time": "",
        "official_website": "https://www.augur.net/",
        "status": "Trading",
        "logo": "../logo/REP.png",
        "address": [
            "0xe28e72fcf78647adce1f1252f240bbfaebd63bcc"
        ],
        "name": "Augur",
        "description": "Prediction market platform",
        "end_time": ""
    },
    {
        "symbol": "SRC",
        "start_time": "26. Apr 2017",
        "official_website": "http://backto.earth/",
        "status": "ICO over",
        "logo": "../logo/SRC.png",
        "address": [],
        "name": "Back to Earth",
        "description": "Cryptocurrency to unlock in-game content",
        "end_time": "28. Apr 2017"
    },
    {
        "symbol": "BGT",
        "start_time": "12. Jun 2017",
        "official_website": "https://www.bancor.network/",
        "status": "ICO coming",
        "logo": "../logo/BGT.png",
        "address": [],
        "name": "BANCOR Network",
        "description": "A hierachical monetary system",
        "end_time": "15. Jul 2017"
    },
    {
        "symbol": "BAT",
        "start_time": "31. May 2017",
        "official_website": "https://basicattentiontoken.org/",
        "status": "ICO over",
        "logo": "../logo/BAT.png",
        "address": [
            "0x0D8775F648430679A709E98d2b0Cb6250d2887EF"
        ],
        "name": "Basic Attention Token",
        "description": "Introducing blockchain-based advertising",
        "end_time": "31. May 2017"
    },
    {
        "symbol": "NEXIUMS",
        "start_time": "1. Nov 2016",
        "official_website": "http://beyond-the-void.net/",
        "status": "ICO over",
        "logo": "../logo/NEXIUMS.png",
        "address": [],
        "name": "Beyond The Void",
        "description": "Real-time strategy video game",
        "end_time": "30. Nov 2016"
    },
    {
        "symbol": "BCAP",
        "start_time": "10. Apr 2017",
        "official_website": "https://blockchaincapital.tokenhub.com/",
        "status": "ICO over",
        "logo": "../logo/BCAP.png",
        "address": [
            "0xff3519eeeea3e76f1f699ccce5e23ee0bdda41ac"
        ],
        "name": "Blockchain Capital",
        "description": "Digital Liquid Venture Fund",
        "end_time": "10. Apr 2017"
    },
    {
        "symbol": "BTX",
        "start_time": "",
        "official_website": "https://blocktix.io/",
        "status": "ICO coming",
        "logo": "../logo/BTX.png",
        "address": [],
        "name": "Blocktix",
        "description": "An Ethereum event hosting platform designed for real world",
        "end_time": ""
    },
    {
        "symbol": "TM-BOARDROOM",
        "start_time": "",
        "official_website": "http://boardroom.to/",
        "status": "",
        "logo": "../logo/TM-BOARDROOM.png",
        "address": [],
        "name": "Boardroom",
        "description": "Blockchain governance platform that empowers organizations",
        "end_time": ""
    },
    {
        "symbol": "BRG",
        "start_time": "",
        "official_website": "https://borgdao.org/",
        "status": "ICO coming",
        "logo": "../logo/BRG.png",
        "address": [],
        "name": "Borg DAO",
        "description": "The Borg DAO will help to stimulate development on Ethereum Classic, by incentivizing developers to support the ETC blockchain for their DApps and to integrate their applications into the Borg DAO.",
        "end_time": ""
    },
    {
        "symbol": "BLT",
        "start_time": "5. Dec 2016",
        "official_website": "https://www.branche.io/",
        "status": "ICO over",
        "logo": "../logo/BLT.png",
        "address": [],
        "name": "Branche",
        "description": "Decentralized Consumer Micro­credit and Financial Services",
        "end_time": "2. Jan 2017"
    },
    {
        "symbol": "LH",
        "start_time": "15. Dec 2016",
        "official_website": "http://chronobank.io/",
        "status": "ICO over",
        "logo": "../logo/LH.png",
        "address": [
            "0x47dfa143923e3e0bd3c3fb6b70e0d2629eb4432d"
        ],
        "name": "ChronoBank",
        "description": "Time based currencies on multiple blockchains",
        "end_time": "15. Feb 2017"
    },
    {
        "symbol": "CVC",
        "start_time": "21. Jun 2017",
        "official_website": "https://tokensale.civic.com/?utm_source=listings&utm_medium=tokenmarket&utm_campaign=tokensale&utm_term=&utm_content=",
        "status": "ICO coming",
        "logo": "../logo/CVC.png",
        "address": [],
        "name": "Civic",
        "description": "Identity verification via the blockchain",
        "end_time": "30. Jun 2017"
    },
    {
        "symbol": "CTT",
        "start_time": "",
        "official_website": "https://launch.codetract.io/",
        "status": "ICO coming",
        "logo": "../logo/CTT.png",
        "address": [
            "0x560c5528ff9886d83Ae117845B180E6DCF6B5175"
        ],
        "name": "CodeTract",
        "description": "Building on Ethereum for mainstream transaction of value",
        "end_time": ""
    },
    {
        "symbol": "CFI",
        "start_time": "7. Jun 2017",
        "official_website": "https://cofound.it/en/",
        "status": "ICO coming",
        "logo": "../logo/CFI.png",
        "address": [],
        "name": "Cofound.it",
        "description": "A distributed VC ecosystem for the distributed future",
        "end_time": "7. Jul 2017"
    },
    {
        "symbol": "BET",
        "start_time": "29. Jun 2017",
        "official_website": "https://dao.casino/",
        "status": "ICO coming",
        "logo": "../logo/BET.png",
        "address": [],
        "name": "DAO.casino",
        "description": "Blockchain protocol for gambling",
        "end_time": "29. Jul 2017"
    },
    {
        "symbol": "DRP",
        "start_time": "1. Jun 2017",
        "official_website": "https://www.dcorp.it/",
        "status": "ICO running",
        "logo": "../logo/DRP.png",
        "address": [
            "0x621d78f2ef2fd937bfca696cabaf9a779f59b3ed"
        ],
        "name": "Dcorp",
        "description": "Derivatives Exchange powered by Ethereum",
        "end_time": "29. Jun 2017"
    },
    {
        "symbol": "DGD",
        "start_time": "",
        "official_website": "https://digix.io/",
        "status": "Trading",
        "logo": "../logo/DGD.png",
        "address": [
            "0xe0b7927c4af23765cb51314a0e0521a9645f0e2a"
        ],
        "name": "DigixDAO",
        "description": "DAO that sells gold with Ethereum based coins",
        "end_time": ""
    },
    {
        "symbol": "E4ROW",
        "start_time": "2. May 2017",
        "official_website": "https://www.e4row.co.il/",
        "status": "ICO over",
        "logo": "../logo/E4ROW.png",
        "address": [
            "0x7b79387dd30dc6848dd2308c825b6802e99abc84"
        ],
        "name": "E4ROW",
        "description": "Ether for the rest of the world",
        "end_time": "23. May 2017"
    },
    {
        "symbol": "EDG",
        "start_time": "28. Feb 2017",
        "official_website": "https://edgeless.io/",
        "status": "ICO over",
        "logo": "../logo/EDG.png",
        "address": [
            "0x08711d3b02c8758f2fb3ab4e80228418a7f8e39c"
        ],
        "name": "Edgeless",
        "description": "Decentralized Casino",
        "end_time": "21. Mar 2017"
    },
    {
        "symbol": "ELCOIN",
        "start_time": "",
        "official_website": "http://7elephant.org/",
        "status": "",
        "logo": "../logo/ELCOIN.png",
        "address": [
            "0x57d90b64a1a57749b0f932f1a3395792e12e7055"
        ],
        "name": "Elephant",
        "description": "Multifunctional economic platform for businesses",
        "end_time": ""
    },
    {
        "symbol": "ETH",
        "start_time": "",
        "official_website": "https://www.ethereum.org/",
        "status": "Trading",
        "logo": "../logo/ETH.png",
        "address": [
            "0xb802b24e0637c2b87d2e8b7784c055bbe921011a"
        ],
        "name": "Ether",
        "description": "Open source platform to write and distribute decentralized applications.",
        "end_time": ""
    },
    {
        "symbol": "TM-ETHERDESIGN",
        "start_time": "",
        "official_website": "http://etherdesign.io/",
        "status": "",
        "logo": "../logo/TM-ETHERDESIGN.png",
        "address": [],
        "name": "Ether Design",
        "description": "Decentralized design sourcing",
        "end_time": ""
    },
    {
        "symbol": "LNK",
        "start_time": "1. May 2017",
        "official_website": "https://ethereum.link/",
        "status": "ICO running",
        "logo": "../logo/LNK.png",
        "address": [],
        "name": "Ethereum.link",
        "description": "Linking ethereum with the world",
        "end_time": "10. Jun 2017"
    },
    {
        "symbol": "ETHEREX",
        "start_time": "",
        "official_website": "https://etherex.org/",
        "status": "ICO coming",
        "logo": "../logo/ETHEREX.png",
        "address": [],
        "name": "Etherex",
        "description": "Fully decentralized cryptocurrency exchange",
        "end_time": ""
    },
    {
        "symbol": "RSC",
        "start_time": "",
        "official_website": "https://camp.etherisc.com/",
        "status": "",
        "logo": "../logo/RSC.png",
        "address": [
            "0x9b0f6a5a667cb92af0cd15dbe90e764e32f69e77"
        ],
        "name": "Etherisc",
        "description": "A decentralized insurance and reinsurance marketplace",
        "end_time": ""
    },
    {
        "symbol": "EXP",
        "start_time": "",
        "official_website": "http://www.expanse.tech/",
        "status": "Trading",
        "logo": "../logo/EXP.png",
        "address": [
            "0x2ba9d006c1d72e67a70b5526fc6b4b0c0fd6d334"
        ],
        "name": "Expanse",
        "description": "Decentralized information, application, and contract platform",
        "end_time": ""
    },
    {
        "symbol": "1ST",
        "start_time": "25. Sep 2016",
        "official_website": "https://firstblood.io/sale/",
        "status": "ICO over",
        "logo": "../logo/1ST.png",
        "address": [
            "0xAf30D2a7E90d7DC361c8C4585e9BB7D2F6f15bc7"
        ],
        "name": "FirstBlood",
        "description": "A token for participating eSports matches and betting",
        "end_time": "26. Sep 2016"
    },
    {
        "symbol": "FND",
        "start_time": "1. Jul 2017",
        "official_website": "https://fundrequest.io/",
        "status": "ICO coming",
        "logo": "../logo/FND.png",
        "address": [],
        "name": "FundRequest",
        "description": "Platform for rewarding open source contributions",
        "end_time": "11. Aug 2017"
    },
    {
        "symbol": "WTT",
        "start_time": "2. Jun 2017",
        "official_website": "https://cryptonomos.com/wtt/",
        "status": "ICO running",
        "logo": "../logo/WTT.png",
        "address": [],
        "name": "Giga Watt",
        "description": "Full-service mining solution provider",
        "end_time": "31. Jul 2017"
    },
    {
        "symbol": "Gnosis",
        "start_time": "24. Apr 2017",
        "official_website": "http://gnosis.pm/",
        "status": "ICO over",
        "logo": "../logo/Gnosis.png",
        "address": [
            "0x6810e776880c02933d47db1b9fc05908e5386b96"
        ],
        "name": "Gnosis",
        "description": "Crowd-sources, ethereum based prediction market",
        "end_time": "24. Apr 2017"
    },
    {
        "symbol": "GNT",
        "start_time": "",
        "official_website": "https://golem.network/",
        "status": "ICO over",
        "logo": "../logo/GNT.png",
        "address": [
            "0xa74476443119A942dE498590Fe1f2454d7D4aC0d"
        ],
        "name": "Golem",
        "description": "Using personal computer to do jobs that are done today by servers",
        "end_time": "13. Nov 2016"
    },
    {
        "symbol": "HKG",
        "start_time": "",
        "official_website": "https://hack.ether.camp/home",
        "status": "",
        "logo": "../logo/HKG.png",
        "address": [],
        "name": "Hacker Gold",
        "description": "Virtual hackathon token",
        "end_time": ""
    },
    {
        "symbol": "Ħ",
        "start_time": "",
        "official_website": "http://www.hongcoin.org/",
        "status": "ICO over",
        "logo": "../logo/Ħ.png",
        "address": [],
        "name": "Hong Coin",
        "description": "Decentralized venture fund on blockchain",
        "end_time": "29. Sep 2016"
    },
    {
        "symbol": "TM-Humaniq Token",
        "start_time": "6. Apr 2017",
        "official_website": "https://humaniq.co/",
        "status": "ICO over",
        "logo": "../logo/TM-Humaniq_Token.png",
        "address": [
            "0xcbcc0f036ed4788f63fc0fee32873d6a7487b908"
        ],
        "name": "Humaniq",
        "description": "Decentralized Banking",
        "end_time": "27. Apr 2017"
    },
    {
        "symbol": "ICN",
        "start_time": "",
        "official_website": "https://ico.iconomi.net",
        "status": "",
        "logo": "../logo/ICN.png",
        "address": [
            "0x888666CA69E0f178DED6D75b5726Cee99A87D698"
        ],
        "name": "Iconomi",
        "description": "Investment fund management platform for the decentralised economy",
        "end_time": ""
    },
    {
        "symbol": "RLC",
        "start_time": "19. Apr 2017",
        "official_website": "http://iex.ec/",
        "status": "ICO over",
        "logo": "../logo/RLC.png",
        "address": [
            "0xec33fB8D7c781F6FeaF2Dd46D521D4F292320200"
        ],
        "name": "iEx.ec",
        "description": "Blockchain-based Fully Distributed Cloud Computing",
        "end_time": "19. Apr 2017"
    },
    {
        "symbol": "INC",
        "start_time": "26. Oct 2016",
        "official_website": "http://ico.inchain.io/",
        "status": "ICO over",
        "logo": "../logo/INC.png",
        "address": [
            "0xda9e3b921db7833bf531ecf899079b6f0aabb360"
        ],
        "name": "InChain",
        "description": "A decentralised insurance platform based on Ethereum smart contracts.",
        "end_time": "26. Nov 2016"
    },
    {
        "symbol": "MIT",
        "start_time": "27. Feb 2017",
        "official_website": "http://www.intellisys.ai/",
        "status": "ICO over",
        "logo": "../logo/MIT.png",
        "address": [],
        "name": "Intellisys",
        "description": "Securitized Blockchain Asset",
        "end_time": "2. Mar 2017"
    },
    {
        "symbol": "KBT",
        "start_time": "",
        "official_website": "http://kiboplatform.net/en/platform.html#!token2",
        "status": "ICO over",
        "logo": "../logo/KBT.png",
        "address": [
            "0x38355ab2667eD167CaDcD132603bc6236c8295de"
        ],
        "name": "Kibo",
        "description": "Decentralized lottery platform based on Ethereum smart-contracts",
        "end_time": "9. Nov 2016"
    },
    {
        "symbol": "TM-KIN",
        "start_time": "",
        "official_website": "https://kin.kik.com/",
        "status": "ICO coming",
        "logo": "../logo/TM-KIN.png",
        "address": [
            "0x96d4F0E75ae86e4c46cD8e9D4AE2F2309bD6Ec45"
        ],
        "name": "Kin",
        "description": "A decentralized ecosystem of digital services for daily life",
        "end_time": ""
    },
    {
        "symbol": "LUN",
        "start_time": "29. Mar 2017",
        "official_website": "https://lunyr.com/",
        "status": "ICO over",
        "logo": "../logo/LUN.png",
        "address": [
            "0xfa05A73FfE78ef8f1a739473e462c54bae6567D9"
        ],
        "name": "Lunyr",
        "description": "Decentralized World Knowledge Base",
        "end_time": "28. Apr 2017"
    },
    {
        "symbol": "GUP",
        "start_time": "2. Apr 2017",
        "official_website": "http://matchpool.co/",
        "status": "ICO over",
        "logo": "../logo/GUP.png",
        "address": [
            "0xE05CeDD2838E4e1d99B539D8C768D6EF2a10F729"
        ],
        "name": "Matchpool",
        "description": "Making human connections",
        "end_time": "4. Apr 2017"
    },
    {
        "symbol": "MLN",
        "start_time": "15. Feb 2017",
        "official_website": "https://melonport.com/",
        "status": "ICO over",
        "logo": "../logo/MLN.png",
        "address": [
            "0xBEB9eF514a379B997e0798FDcC901Ee474B6D9A1"
        ],
        "name": "Melon",
        "description": "Blockchain software for asset management",
        "end_time": "16. Feb 2017"
    },
    {
        "symbol": "METAL",
        "start_time": "10. Jun 2017",
        "official_website": "https://www.metalpay.co/",
        "status": "ICO coming",
        "logo": "../logo/METAL.png",
        "address": [],
        "name": "Metal",
        "description": "Earn rewards every time you send or spend.",
        "end_time": "10. Jul 2017"
    },
    {
        "symbol": "MCO",
        "start_time": "18. May 2017",
        "official_website": "https://mona.co/",
        "status": "ICO running",
        "logo": "../logo/MCO.png",
        "address": [
            "0xb04cfa8a26d602fb50232cee0daf29060264e04b"
        ],
        "name": "Monaco",
        "description": "Best world's cryptocurrency card",
        "end_time": "18. Jun 2017"
    },
    {
        "symbol": "MyB",
        "start_time": "27. Jun 2017",
        "official_website": "https://mybit.io/",
        "status": "ICO coming",
        "logo": "../logo/MyB.png",
        "address": [],
        "name": "MyBit",
        "description": "Decentralized Asset Management w/ AI & Smart Financing",
        "end_time": "27. Jul 2017"
    },
    {
        "symbol": "MYST",
        "start_time": "30. May 2017",
        "official_website": "https://mysterium.network/",
        "status": "ICO running",
        "logo": "../logo/MYST.png",
        "address": [
            "0x4f529990b7f3d1fb4152736155e431c96fd86294"
        ],
        "name": "Mysterium Network",
        "description": "Decentralised VPN service built on blockchain",
        "end_time": "30. May 2017"
    },
    {
        "symbol": "TM- NAPOLEON",
        "start_time": "",
        "official_website": "http://napoleoncapital.com/",
        "status": "ICO coming",
        "logo": "../logo/TM-_NAPOLEON.png",
        "address": [],
        "name": "Napoleon Capital",
        "description": "Smart Trading Bots",
        "end_time": ""
    },
    {
        "symbol": "NMR",
        "start_time": "",
        "official_website": "https://numer.ai/",
        "status": "",
        "logo": "../logo/NMR.png",
        "address": [],
        "name": "Numerai",
        "description": "A new kind of hedge fund",
        "end_time": ""
    },
    {
        "symbol": "OMG",
        "start_time": "",
        "official_website": "https://omg.omise.co/",
        "status": "ICO coming",
        "logo": "../logo/OMG.png",
        "address": [],
        "name": "Omise GO",
        "description": "Help us bank the unbanked, the right way",
        "end_time": ""
    },
    {
        "symbol": "OAX",
        "start_time": "22. Jun 2017",
        "official_website": "https://www.openanx.org/",
        "status": "ICO coming",
        "logo": "../logo/OAX.png",
        "address": [],
        "name": "openANX",
        "description": "Real World Application of Decentralized Exchanges",
        "end_time": "21. Jul 2017"
    },
    {
        "symbol": "OROC",
        "start_time": "14. Jun 2017",
        "official_website": "https://orocrypt.com/",
        "status": "ICO coming",
        "logo": "../logo/OROC.png",
        "address": [],
        "name": "Orocrypt",
        "description": "Digitized Precious Metals On The Ethereum Blockchain",
        "end_time": "14. Jul 2017"
    },
    {
        "symbol": "PSLFX",
        "start_time": "2. Dec 2016",
        "official_website": "http://pacifics.org/",
        "status": "ICO over",
        "logo": "../logo/PSLFX.png",
        "address": [],
        "name": "PassLfix",
        "description": "Smart contract ethereum based parcel delivery.",
        "end_time": "1. Jan 2017"
    },
    {
        "symbol": "PTOY",
        "start_time": "31. May 2017",
        "official_website": "http://www.patientory.com/",
        "status": "ICO over",
        "logo": "../logo/PTOY.png",
        "address": [],
        "name": "Patientory",
        "description": "Blockchain-secured medical records",
        "end_time": "3. Jun 2017"
    },
    {
        "symbol": "PPT",
        "start_time": "16. Jul 2017",
        "official_website": "http://www.populous.co/",
        "status": "ICO coming",
        "logo": "../logo/PPT.png",
        "address": [],
        "name": "Populous",
        "description": "Invoice finance and factoring in blockchain",
        "end_time": "15. Aug 2017"
    },
    {
        "symbol": "OBT",
        "start_time": "1. Jun 2017",
        "official_website": "https://prospectors.io/en",
        "status": "ICO running",
        "logo": "../logo/OBT.png",
        "address": [],
        "name": "Prospectors",
        "description": "Massive multiplayer online real time economic strategy",
        "end_time": "1. Jul 2017"
    },
    {
        "symbol": "REI",
        "start_time": "",
        "official_website": "http://www.reidao.io/",
        "status": "ICO coming",
        "logo": "../logo/REI.png",
        "address": [],
        "name": "ReiDAO",
        "description": "Digitalizing real estate ownerships",
        "end_time": ""
    },
    {
        "symbol": "REX",
        "start_time": "",
        "official_website": "http://rexmls.com/",
        "status": "ICO coming",
        "logo": "../logo/REX.png",
        "address": [
            "0x42a689F1eBFcA404E13c29Cb6D01e00059ba9dbC"
        ],
        "name": "Rex",
        "description": "Real Estate Revolution",
        "end_time": ""
    },
    {
        "symbol": "SNT",
        "start_time": "30. Jun 2017",
        "official_website": "http://www.santiment.net/",
        "status": "ICO over",
        "logo": "../logo/SNT.png",
        "address": [
            "0x4fd997ed7c10dbd04e95d3730cd77d79513076f2"
        ],
        "name": "Santiment",
        "description": "Cryptomarkets intelligence platform",
        "end_time": "13. Feb 2017"
    },
    {
        "symbol": "SHIFT",
        "start_time": "",
        "official_website": "http://www.shiftnrg.org/",
        "status": "Trading",
        "logo": "../logo/SHIFT.png",
        "address": [
            "0x120a270bbc009644e35f0bb6ab13f95b8199c4ad"
        ],
        "name": "Shift",
        "description": "A network for decentralized applications",
        "end_time": ""
    },
    {
        "symbol": "TM-SIKOBA",
        "start_time": "24. Apr 2017",
        "official_website": "http://www.sikoba.com/www/",
        "status": "ICO running",
        "logo": "../logo/TM-SIKOBA.png",
        "address": [
            "0x4994e81897a920c0fea235eb8cedeed3c6fff697"
        ],
        "name": "Sikoba",
        "description": "A P2P IOU/credit platform",
        "end_time": "24. May 2017"
    },
    {
        "symbol": "SNGLS",
        "start_time": "5. Oct 2016",
        "official_website": "https://singulardtv.com/sign-up",
        "status": "Trading",
        "logo": "../logo/SNGLS.png",
        "address": [
            "0xe736091fc36f1ad476f5e4e03e4425940822d3ba"
        ],
        "name": "SingularDTV",
        "description": "Blockchain film and television studio & distribution portal",
        "end_time": "29. Oct 2016"
    },
    {
        "symbol": "SPT",
        "start_time": "15. Jun 2017",
        "official_website": "https://sonm.io/",
        "status": "ICO coming",
        "logo": "../logo/SPT.png",
        "address": [],
        "name": "SONM Network",
        "description": "Supercomputer Organized by Network Mining (GRIB technology)",
        "end_time": "15. Jul 2017"
    },
    {
        "symbol": "STAR",
        "start_time": "1. Jul 2017",
        "official_website": "https://starbase.co/",
        "status": "ICO coming",
        "logo": "../logo/STAR.png",
        "address": [],
        "name": "Starbase",
        "description": "Blockchain token based crowdfunding/crowdsourcing platform",
        "end_time": "15. Aug 2017"
    },
    {
        "symbol": "TM-Status",
        "start_time": "",
        "official_website": "https://status.im/",
        "status": "ICO coming",
        "logo": "../logo/TM-Status.png",
        "address": [
            "0xd248b0d48e44aaf9c49aea0312be7e13a6dc1468"
        ],
        "name": "Status",
        "description": "Status is a browser, messenger, and gateway to a decentralised world.",
        "end_time": ""
    },
    {
        "symbol": "SJCX",
        "start_time": "19. May 2017",
        "official_website": "https://storj.io/tokensale",
        "status": "Trading",
        "logo": "../logo/SJCX.png",
        "address": [
            "0xe75509810e09b04eef4ebd0b471bacf5530b162e"
        ],
        "name": "Storj",
        "description": "Decentralized cloud storage platform",
        "end_time": "25. May 2017"
    },
    {
        "symbol": "TAAS",
        "start_time": "27. Mar 2017",
        "official_website": "http://taas.fund/",
        "status": "ICO over",
        "logo": "../logo/TAAS.png",
        "address": [
            "0xe7775a6e9bcf904eb39da2b68c5efb4f9360e08c"
        ],
        "name": "TaaS",
        "description": "Token as a Service",
        "end_time": "28. Apr 2017"
    },
    {
        "symbol": "TM-TENX",
        "start_time": "",
        "official_website": "https://www.tenx.tech/",
        "status": "ICO coming",
        "logo": "../logo/TM-TENX.png",
        "address": [],
        "name": "TenX",
        "description": "Connected blockchain",
        "end_time": ""
    },
    {
        "symbol": "VIP",
        "start_time": "18. Apr 2017",
        "official_website": "http://legendsroomlv.com/",
        "status": "ICO over",
        "logo": "../logo/VIP.png",
        "address": [
            "0xb939ef33629bba211688724e401d4f6400c0ee6a"
        ],
        "name": "The Legends Room",
        "description": "Las Vegas Nightlife Using Blockchain Technology",
        "end_time": "20. May 2017"
    },
    {
        "symbol": "TKN",
        "start_time": "2. May 2017",
        "official_website": "http://tokencard.io/",
        "status": "ICO over",
        "logo": "../logo/TKN.png",
        "address": [
            "0xaaaf91d9b90df800df4f55c205fd6989c977e73a"
        ],
        "name": "TokenCard",
        "description": "A platform for the post-bank era",
        "end_time": "2. May 2017"
    },
    {
        "symbol": "TM-TAG",
        "start_time": "",
        "official_website": "http://transactivegrid.net/",
        "status": "",
        "logo": "../logo/TM-TAG.png",
        "address": [],
        "name": "TransActive Grid",
        "description": "Community energy market enabled by the blockchain",
        "end_time": ""
    },
    {
        "symbol": "TM-TrueBit",
        "start_time": "",
        "official_website": "http://www.truebit.io/",
        "status": "ICO coming",
        "logo": "../logo/TM-TrueBit.png",
        "address": [],
        "name": "TrueBit",
        "description": "A scalable verification solution for blockchains",
        "end_time": ""
    },
    {
        "symbol": "TFL",
        "start_time": "20. Apr 2017",
        "official_website": "http://trueflip.io/ico?lang=en",
        "status": "ICO over",
        "logo": "../logo/TFL.png",
        "address": [],
        "name": "True Flip Lottery",
        "description": "Blockchain lottery",
        "end_time": "15. May 2017"
    },
    {
        "symbol": "UBQ",
        "start_time": "",
        "official_website": "https://ubiqsmart.com/",
        "status": "Trading",
        "logo": "../logo/UBQ.png",
        "address": [],
        "name": "Ubiq",
        "description": "Smart Contracts For An Automated World",
        "end_time": ""
    },
    {
        "symbol": "vSlice",
        "start_time": "15. Nov 2016",
        "official_website": "https://www.vdice.io/",
        "status": "ICO over",
        "logo": "../logo/vSlice.png",
        "address": [
            "0x5c543e7AE0A1104f78406C340E9C64FD9fCE5170"
        ],
        "name": "vDice.io",
        "description": "Ethereum based betting game",
        "end_time": "15. Dec 2016"
    },
    {
        "symbol": "VEGA token",
        "start_time": "",
        "official_website": "http://www.vega.fund/",
        "status": "ICO coming",
        "logo": "../logo/VEGA_token.png",
        "address": [],
        "name": "Vega",
        "description": "Decentralized Effective Funding",
        "end_time": ""
    },
    {
        "symbol": "TM-VEVUE",
        "start_time": "",
        "official_website": "http://www.govevue.com/",
        "status": "",
        "logo": "../logo/TM-VEVUE.png",
        "address": [],
        "name": "Vevue Project",
        "description": "Crowdsourced videos from around the world",
        "end_time": ""
    },
    {
        "symbol": "WGR",
        "start_time": "1. Jun 2017",
        "official_website": "",
        "status": "ICO running",
        "logo": "../logo/WGR.png",
        "address": [],
        "name": "Wagerr",
        "description": "A betting blockchain",
        "end_time": "25. Jun 2017"
    },
    {
        "symbol": "TM-WEI",
        "start_time": "",
        "official_website": "http://weifund.io/",
        "status": "",
        "logo": "../logo/TM-WEI.png",
        "address": [],
        "name": "WeiFund",
        "description": "A non-profit, decentralized, open-source equity crowdfunding platform built on Ethereum",
        "end_time": ""
    },
    {
        "symbol": "TRST",
        "start_time": "2. Mar 2017",
        "official_website": "https://www.wetrust.io/",
        "status": "ICO over",
        "logo": "../logo/TRST.png",
        "address": [
            "0xc2cce1f4190d4451c63cf591678c807679c3d728"
        ],
        "name": "WeTrust",
        "description": "Savings & Insurance Platform",
        "end_time": "14. Apr 2017"
    }
]
